livekit/plugins/speechmatics/__init__.py
livekit/plugins/speechmatics/log.py
livekit/plugins/speechmatics/py.typed
livekit/plugins/speechmatics/stt.py
livekit/plugins/speechmatics/tts.py
livekit/plugins/speechmatics/types.py
livekit/plugins/speechmatics/utils.py
livekit/plugins/speechmatics/version.py
livekit_plugins_speechmatics-1.3.11.dist-info/METADATA
livekit_plugins_speechmatics-1.3.11.dist-info/WHEEL
livekit_plugins_speechmatics-1.3.11.dist-info/RECORD
